codeviewx/__init__.py
codeviewx/__version__.py
codeviewx/cli.py
codeviewx/core.py
codeviewx/generator.py
codeviewx/i18n.py
codeviewx/language.py
codeviewx/prompt.py
codeviewx/server.py
codeviewx/prompts/__init__.py
codeviewx/prompts/document_engineer.md
codeviewx/prompts/document_engineer_zh.md
codeviewx/static/css/common.css
codeviewx/static/css/typo.css
codeviewx/tools/__init__.py
codeviewx/tools/command.py
codeviewx/tools/filesystem.py
codeviewx/tools/search.py
codeviewx/tpl/doc_detail.html
codeviewx-0.2.8.dist-info/licenses/LICENSE
codeviewx-0.2.8.dist-info/METADATA
codeviewx-0.2.8.dist-info/WHEEL
codeviewx-0.2.8.dist-info/entry_points.txt
codeviewx-0.2.8.dist-info/top_level.txt
codeviewx-0.2.8.dist-info/RECORD
