Metadata-Version: 2.4
Name: codeviewx
Version: 0.2.8
Summary: AI-powered code documentation generator based on DeepAgents and LangChain
Author: CodeViewX Team
License: GPL-3.0-or-later
Project-URL: Homepage, https://github.com/dean2021/codeviewx
Project-URL: Documentation, https://github.com/dean2021/codeviewx/tree/main/docs
Project-URL: Repository, https://github.com/dean2021/codeviewx
Project-URL: Bug Tracker, https://github.com/dean2021/codeviewx/issues
Keywords: documentation,ai,code-analysis,deepagents,langchain,code-documentation,document-generation
Classifier: Development Status :: 3 - Alpha
Classifier: Intended Audience :: Developers
Classifier: License :: OSI Approved :: GNU General Public License v3 or later (GPLv3+)
Classifier: Programming Language :: Python :: 3
Classifier: Programming Language :: Python :: 3.8
Classifier: Programming Language :: Python :: 3.9
Classifier: Programming Language :: Python :: 3.10
Classifier: Programming Language :: Python :: 3.11
Classifier: Programming Language :: Python :: 3.12
Classifier: Topic :: Documentation
Classifier: Topic :: Software Development :: Documentation
Classifier: Topic :: Software Development :: Libraries :: Python Modules
Classifier: Environment :: Console
Requires-Python: >=3.8
License-File: LICENSE
Requires-Dist: anthropic==0.70.0
Requires-Dist: deepagents==0.0.5
Requires-Dist: langchain==0.3.27
Requires-Dist: langchain-anthropic==0.3.22
Requires-Dist: langchain-core==0.3.79
Requires-Dist: langchain-text-splitters==0.3.11
Requires-Dist: langgraph==0.6.10
Requires-Dist: langgraph-checkpoint==2.1.2
Requires-Dist: langgraph-prebuilt==0.6.4
Requires-Dist: langgraph-sdk==0.2.9
Requires-Dist: langsmith==0.4.34
Requires-Dist: Pygments==2.19.2
Requires-Dist: PyYAML==6.0.3
Requires-Dist: requests==2.32.5
Requires-Dist: requests-toolbelt==1.0.0
Requires-Dist: ripgrepy==2.2.0
Requires-Dist: flask>=2.0.0
Requires-Dist: markdown>=3.4.0
Requires-Dist: pymdown-extensions>=10.5
Provides-Extra: dev
Requires-Dist: pytest==8.4.2; extra == "dev"
Requires-Dist: pytest-cov>=4.0; extra == "dev"
Requires-Dist: black>=23.0; extra == "dev"
Requires-Dist: flake8>=6.0; extra == "dev"
Requires-Dist: mypy>=1.0; extra == "dev"
Requires-Dist: isort>=5.0; extra == "dev"
Requires-Dist: build>=0.10.0; extra == "dev"
Requires-Dist: twine>=4.0.0; extra == "dev"
Dynamic: license-file
